adl_recognition/__init__.py
adl_recognition/audio_data.py
adl_recognition/depth_data.py
adl_recognition/model.py
adl_recognition/predict.py
adl_recognition/models/15_07_14_acc_92.h5
adl_recognition/models/15_07_14_acc_92.json
adl_recognition/models/2019_09_27_02_56_29_2.h5
adl_recognition/models/2019_09_27_02_56_29_2.json
adl_recognition-1.0.1.dist-info/LICENCE
adl_recognition-1.0.1.dist-info/METADATA
adl_recognition-1.0.1.dist-info/WHEEL
adl_recognition-1.0.1.dist-info/top_level.txt
adl_recognition-1.0.1.dist-info/RECORD
