Metadata-Version: 2.1
Name: adl-recognition
Version: 1.0.1
Summary: Classification of Activities of Daily Living(ADL) using depth videos and audio
Home-page: https://github.com/RivinduM/AdlRecognition
Author: Rivindu Madushan <rivindum.15@cse.mrt.ac.lk>, Danushka Madhuranga <danushka.15@cse.mrt.ac.lk>, Chathuranga Siriwwardana <chathuranga.15@cse.mrt.ac.lk>
Author-email: rivindum.15@cse.mrt.ac.lk
License: UNKNOWN
Platform: UNKNOWN
Classifier: Programming Language :: Python :: 3
Classifier: License :: OSI Approved :: MIT License
Classifier: Operating System :: OS Independent
Requires-Python: >=2.7
Requires-Dist: numpy (>=1.17.2)
Requires-Dist: librosa (>=0.6.0)
Requires-Dist: noisereduce (>=1.0.0)
Requires-Dist: opencv-python (>=4.1.1.26)
Requires-Dist: keras (>=2.2.0)
